.pre-commit-config.yaml
AUTHORS
ChangeLog
README.md
requirements.txt
setup.cfg
setup.py
tests/test_client.py
tourbillon_client/__init__.py
tourbillon_client.egg-info/PKG-INFO
tourbillon_client.egg-info/SOURCES.txt
tourbillon_client.egg-info/dependency_links.txt
tourbillon_client.egg-info/not-zip-safe
tourbillon_client.egg-info/pbr.json
tourbillon_client.egg-info/requires.txt
tourbillon_client.egg-info/top_level.txt