Metadata-Version: 1.1
Name: tourbillon-client
Version: 0.0.1.dev3
Summary: client for the tourbillon service
Home-page: https://etsgitlab.westeurope.cloudapp.azure.com/clients/tourbillon-client
Author: See AUTHORS
Author-email: eric@adimian.com
License: MIT/Expat
Platform: UNKNOWN
Classifier: Development Status :: 4 - Beta
Classifier: Operating System :: MacOS :: MacOS X
Classifier: Operating System :: Microsoft :: Windows
Classifier: Operating System :: POSIX
Classifier: License :: OSI Approved :: MIT License
Classifier: Programming Language :: Python
Classifier: Programming Language :: Python :: 2.7
Classifier: Programming Language :: Python :: 3.4
Classifier: Programming Language :: Python :: 3.5
